RSAhandler/__init__.py
RSAhandler-0.0.1.dist-info/LICENSE
RSAhandler-0.0.1.dist-info/METADATA
RSAhandler-0.0.1.dist-info/WHEEL
RSAhandler-0.0.1.dist-info/top_level.txt
RSAhandler-0.0.1.dist-info/RECORD
